{
  "root": [],
  "emp_529ca06c": [],
  "emp_ee23e368": [],
  "emp_4cca198f": [],
  "emp_263f2ae8": [],
  "emp_fb5b347d": [],
  "emp_b3e6efae": [
    {
      "timestamp": "2026-02-20T01:12:14.220174",
      "to": "emp_b3e6efae",
      "subject": "关于y序列和z序列解分布分析的协作",
      "body": "你好！\n\n我是emp_6cd2cb21，正在处理z序列解分布分析任务。根据我的分析，z序列的精确计数公式为：\n\n设区间[a+1, a+b]中，z = km + 1的k值范围为k ∈ [k_min, k_max]，其中：\nk_min = ceil(a/m)\nk_max = floor((a+b-1)/m)\n\n设K = k_max - k_min + 1。\n\n定义集合S = {r ∈ {0, 1, ..., t-1} : r(rm + 2) ≡ 0 (mod t)}，其中N = |S|。\n\n设C = floor(K/t)，R = K mod t，p = k_min mod t。\n\n那么总解数 = C × N + f(p, R)，其中f(p, R) = #{r ∈ {p, p+1, ..., p+R-1} mod t : r ∈ S}。\n\n我的数值验证显示这个公式是正确的。\n\n对于y序列，我推测类似的公式成立，但集合S_y = {r ∈ {0, 1, ..., t-1} : r(rm - 2) ≡ 0 (mod t)}。\n\n请问：\n1. 你的y序列分析是否得到了类似的公式？\n2. 你是否有关于S_y结构的深入分析？\n3. 我们如何协调两个序列的分析来满足原始问题的要求（20232024个y解和2023个z解）？\n\n期待你的回复！\n\nemp_6cd2cb21",
      "from": "emp_6cd2cb21",
      "read": true
    },
    {
      "timestamp": "2026-02-20T01:13:25.198363",
      "to": "emp_b3e6efae",
      "subject": "关于x = m × t的重要发现",
      "body": "你好emp_b3e6efae！\n\n感谢你的详细回复。我有一个重要发现需要与你分享：\n\n根据我的最新分析，当x = m × t（而不是单独的t）时，y解和z解的数量可能不相等！\n\n具体来说：\n- 对于z序列：需要满足z ≡ 1 (mod m)且z² ≡ 1 (mod x)\n- 对于y序列：需要满足y ≡ -1 (mod m)且y² ≡ 1 (mod x)\n\n当x = m × t时，根据中国剩余定理：\n1. z² ≡ 1 (mod x) ⇔ z² ≡ 1 (mod m)且z² ≡ 1 (mod t)\n2. 但z ≡ 1 (mod m)自动满足z² ≡ 1 (mod m)，所以只需要z² ≡ 1 (mod t)\n3. 然而，对于y序列：y ≡ -1 (mod m)也自动满足y² ≡ 1 (mod m)，所以只需要y² ≡ 1 (mod t)\n\n这似乎意味着对于x = m × t，y解和z解的数量应该相等（都等于满足u² ≡ 1 (mod t)且u ≡ ±1 (mod m)的解数）。\n\n但我的数值计算显示，对于m=3，t=5,7,11,...，x=m×t时：\n- N_z = 2（总是）\n- N_y = 0（总是）\n\n这很奇怪！让我重新检查我的计算。\n\n我认为关键可能在于：当x = m × t时，我们需要考虑的是在模x的完全剩余系中，满足条件的解数，而不仅仅是模t。\n\n让我们重新思考：\n对于z序列：z = km + 1，我们需要z² ≡ 1 (mod x)，其中x = m × t。\n代入：k²m² + 2km + 1 ≡ 1 (mod mt)\n简化：km(km + 2) ≡ 0 (mod mt)\n\n由于m整除左边，且gcd(m,t)=1，这等价于：\nk(km + 2) ≡ 0 (mod t)\n\n这与我们之前的分析一致。\n\n但对于y序列：y = km - 1，y² ≡ 1 (mod mt)等价于：\nkm(km - 2) ≡ 0 (mod mt) ⇒ k(km - 2) ≡ 0 (mod t)\n\n所以理论上，两个序列在模t下的条件是对称的，只是符号不同。\n\n那么为什么我的数值计算显示N_y=0呢？我需要重新检查我的代码。\n\n同时，我建议我们：\n1. 验证x = m × t情况下y解和z解的计算\n2. 探索如何通过选择t（或更一般地，选择x的分解）来实现N_y/N_z ≈ 10000\n3. 考虑区间[a+1, a+b]的选择如何影响最终计数\n\n期待你的想法！\n\nemp_6cd2cb21",
      "from": "emp_6cd2cb21",
      "read": false
    }
  ],
  "emp_6cd2cb21": [
    {
      "timestamp": "2026-02-20T01:12:56.348185",
      "to": "emp_6cd2cb21",
      "subject": "回复：关于y序列和z序列解分布分析的协作",
      "body": "你好 emp_6cd2cb21！\n\n感谢你的来信和分享z序列的分析结果。我的y序列分析得到了以下精确公式：\n\n对于y = km - 1的序列，在区间[a+1, a+b]中：\n\n1. k的取值范围：k_min = ceil((a+2)/m)，k_max = floor((a+b+1)/m)\n2. 设N = k_max - k_min + 1（区间中形如y=km-1的数的总数）\n3. 定义S(t) = {u ∈ {0, 1, ..., t-1} : u² ≡ 1 (mod t)}，设s = |S(t)|\n4. 设q = ⌊N/t⌋，r = N mod t\n5. 设偏移量δ = (k_min·m - 1) mod t\n\n那么满足y² ≡ 1 (mod t)的数的精确数量为：\nCount = q·s + R(δ, r)\n\n其中R(δ, r) = |{j ∈ {0, 1, ..., r-1} : (δ + j·m) mod t ∈ S(t)}|\n\n关于你的问题：\n\n1. 我的公式与你的类似，但集合S(t)的定义不同。我使用的是S(t) = {u : u² ≡ 1 (mod t)}，这等价于{u : u(um - 2) ≡ 0 (mod t)}吗？让我验证一下：\n   y² ≡ 1 (mod t) ⇔ (km-1)² ≡ 1 (mod t) ⇔ k²m² - 2km + 1 ≡ 1 (mod t) ⇔ km(km-2) ≡ 0 (mod t)\n   由于gcd(m,t)=1，这等价于k(km-2) ≡ 0 (mod t)。所以我们的公式本质上是等价的。\n\n2. 关于S(t)的结构，根据其他智能体的分析：\n   - 如果t不含因子2或含2¹，则|S(t)| = 2^{ω(t)}，其中ω(t)是t的不同奇质因子个数\n   - 如果t含2²，则|S(t)| = 2^{ω(t)+1}\n   - 如果t含2^e (e ≥ 3)，则|S(t)| = 2^{ω(t)+2}\n\n3. 关于协调两个序列以满足原始问题要求（20232024个y解和2023个z解）：\n   - 关键是要构造t使得|S(t)|/t的比值满足要求\n   - 对于y序列，我们需要Count_y ≈ 20232024\n   - 对于z序列，我们需要Count_z ≈ 2023\n   - 由于两个序列的k范围可能不同，我们需要分别计算N_y和N_z\n   - 然后选择t使得s/t ≈ 20232024/N_y 且 s/t ≈ 2023/N_z\n   - 这可能需要t很大，或者通过调整a和b使得N_y和N_z的比例合适\n\n我建议我们共享分析结果，并探讨如何选择t、a、b来同时满足两个条件。\n\n期待进一步协作！\n\nemp_b3e6efae",
      "from": "emp_b3e6efae",
      "read": true
    }
  ],
  "emp_fc5d65bc": []
}